[
	{ "s": "0", "p": [84, 12, 102, 90, 89, 59, 42, 13, 107, 106, 58, 10, 9] },
	{ "s": "0.00004", "p": [12] },
	{ "s": "0.00067", "p": [12] },
	{ "s": "0.00133", "p": [12] },
	{ "s": "0.00167", "p": [12] },
	{ "s": "0.003", "p": [10] },
	{ "s": "0.05", "p": [107, 90, 89] },
	{ "s": "0.06054", "p": [84] },
	{ "s": "0.07", "p": [84] },
	{ "s": "0.07972", "p": [102] },
	{ "s": "0.1", "p": [42] },
	{ "s": "0.10", "p": [84, 106] },
	{ "s": "0.13", "p": [84] },
	{ "s": "0.15", "p": [84] },
	{ "s": "0.23", "p": [13] },
	{ "s": "0.25", "p": [84, 59] },
	{ "s": "0.26", "p": [102] },
	{ "s": "0.27", "p": [102] },
	{ "s": "0.3", "p": [42] },
	{ "s": "0.30", "p": [90, 84] },
	{ "s": "0.34", "p": [84] },
	{ "s": "0.35", "p": [13] },
	{ "s": "0.5", "p": [58] },
	{ "s": "0.50", "p": [90, 89] },
	{ "s": "0.60116", "p": [84] },
	{ "s": "00", "p": [89, 106, 90, 107, 84, 9, 102, 58, 41, 13, 12, 10] },
	{ "s": "000", "p": [41, 13] },
	{ "s": "000.00", "p": [41] },
	{ "s": "00004", "p": [12] },
	{ "s": "00067", "p": [12] },
	{ "s": "001", "p": [26, 23, 25, 84, 24, 90, 89, 39, 38, 22, 102, 41, 165, 160, 107, 106, 104, 86, 73, 71, 56, 54, 42, 37, 35, 21, 10, 6] },
	{ "s": "00133", "p": [12] },
	{ "s": "00167", "p": [12] },
	{ "s": "002", "p": [35, 44, 58, 43, 37, 90, 89, 84, 59, 54, 34, 88, 42, 38, 26, 25, 167, 162, 107, 106, 102, 87, 57, 41, 21, 12] },
	{ "s": "003", "p": [54, 61, 60, 56, 53, 89, 57, 44, 43, 90, 88, 59, 21, 10] },
	{ "s": "004", "p": [71, 75, 74, 73, 70, 106, 44, 43, 107, 105, 21] },
	{ "s": "005", "p": [84, 92, 91, 86, 83, 90, 87, 61, 60, 89, 21] },
	{ "s": "006", "p": [102, 109, 108, 165, 160, 104, 167, 162, 101, 107, 105, 61, 60, 106, 90, 89, 84, 21, 12] },
	{ "s": "007", "p": [118, 75, 74, 21, 12] },
	{ "s": "008", "p": [130, 75, 74, 21] },
	{ "s": "009", "p": [142, 92, 91, 107, 106, 102, 90, 89, 84, 21] },
	{ "s": "01", "p": [13] },
	{ "s": "010", "p": [147, 92, 91, 21] },
	{ "s": "010207", "p": [12] },
	{ "s": "010302", "p": [12] },
	{ "s": "010401", "p": [12] },
	{ "s": "011", "p": [109, 108] },
	{ "s": "012", "p": [109, 108] },
	{ "s": "014", "p": [90, 89, 84, 12] },
	{ "s": "016", "p": [107, 106, 102, 90, 89, 84] },
	{ "s": "02", "p": [102, 90, 89, 84] },
	{ "s": "020731", "p": [10] },
	{ "s": "021", "p": [107, 106, 102] },
	{ "s": "022", "p": [90, 89, 84] },
	{ "s": "029", "p": [12] },
	{ "s": "030", "p": [84] },
	{ "s": "031", "p": [90, 89, 84] },
	{ "s": "040103", "p": [13] },
	{ "s": "040212", "p": [13] },
	{ "s": "040217", "p": [13] },
	{ "s": "040218", "p": [13] },
	{ "s": "040219", "p": [13] },
	{ "s": "040221", "p": [13] },
	{ "s": "040317", "p": [13] },
	{ "s": "040404", "p": [13] },
	{ "s": "05", "p": [12, 84, 107, 90, 89] },
	{ "s": "050", "p": [89] },
	{ "s": "054", "p": [90, 89, 84] },
	{ "s": "06", "p": [102] },
	{ "s": "06054", "p": [84] },
	{ "s": "07", "p": [84] },
	{ "s": "07972", "p": [102] },
	{ "s": "09", "p": [13] }
]